rss2email/__init__.py
rss2email/command.py
rss2email/config.py
rss2email/email.py
rss2email/error.py
rss2email/feed.py
rss2email/feeds.py
rss2email/main.py
rss2email/util.py
rss2email/version.py
rss2email/post_process/__init__.py
rss2email/post_process/downcase.py
rss2email/post_process/prettify.py
rss2email/post_process/redirect.py
rss2email-3.14.data/scripts/r2e
rss2email-3.14.dist-info/AUTHORS
rss2email-3.14.dist-info/COPYING
rss2email-3.14.dist-info/METADATA
rss2email-3.14.dist-info/WHEEL
rss2email-3.14.dist-info/top_level.txt
rss2email-3.14.dist-info/RECORD
