Metadata-Version: 2.1
Name: rss2email
Version: 3.14
Summary: A python script that converts RSS/Atom newsfeeds to email
Home-page: https://github.com/rss2email/rss2email
Download-URL: https://github.com/rss2email/rss2email/archive/v3.14.tar.gz
Maintainer: The rss2email maintainers
Maintainer-email: rss2email@tremily.us
License: GNU General Public License (GPL)
Platform: all
Classifier: Development Status :: 5 - Production/Stable
Classifier: Environment :: Console
Classifier: Intended Audience :: End Users/Desktop
Classifier: Operating System :: OS Independent
Classifier: License :: OSI Approved :: GNU General Public License (GPL)
Classifier: License :: OSI Approved :: GNU General Public License v2 (GPLv2)
Classifier: License :: OSI Approved :: GNU General Public License v3 (GPLv3)
Classifier: Programming Language :: Python
Classifier: Programming Language :: Python :: 3
Classifier: Programming Language :: Python :: 3.6
Classifier: Programming Language :: Python :: 3.7
Classifier: Programming Language :: Python :: 3.8
Classifier: Topic :: Communications :: Email
Classifier: Topic :: Software Development :: Libraries :: Python Modules
Provides: rss2email
License-File: COPYING
License-File: AUTHORS
Requires-Dist: feedparser (>=6.0.5)
Requires-Dist: html2text (>=2020.1.16)
